{
   "speakers" : [
      {
        "name" : "Addy Osmani",
        "shortname" : "Addy Osmani",
        "reknown" : "Yeoman & DevTools, Creator of TodoMVC, Aura, Basket",
        "bio" : " Passionate about pushing the web forward…"
      }
      {
        "name" : "Paul Irish",
        "shortname" : "Paul Irish",
        "reknown" : ,
        "bio" :
      }
      {
        "name" : ,
        "shortname" : ,
        "reknown" : ,
        "bio" :
      }
      {
        "name" : ,
        "shortname" : ,
        "reknown" : ,
        "bio" :
      }
      {
        "name" : ,
        "shortname" : ,
        "reknown" : ,
        "bio" :
      }
      {
        "name" : ,
        "shortname" : ,
        "reknown" : ,
        "bio" :
      }
      {
        "name" : ,
        "shortname" : ,
        "reknown" : ,
        "bio" :
      }


   ]
}  